LICENSE.txt
binobj/__init__.py
binobj/dataclass_compat.p_
binobj/dataclass_interface.p_
binobj/decorators.py
binobj/errors.py
binobj/fields/__init__.py
binobj/fields/base.py
binobj/fields/containers.py
binobj/fields/numeric.py
binobj/fields/stringlike.py
binobj/helpers.py
binobj/pep526.py
binobj/py.typed
binobj/structures.py
binobj/typedefs.py
binobj/varints.py
binobj-0.12.0.dist-info/LICENSE.txt
binobj-0.12.0.dist-info/METADATA
binobj-0.12.0.dist-info/WHEEL
binobj-0.12.0.dist-info/RECORD
