Metadata-Version: 2.1
Name: binobj
Version: 0.12.0
Summary: A Python library for reading and writing structured binary data.
License: BSD-3-Clause
Author: Diego Argueta
Author-email: 620513-dargueta@users.noreply.github.com
Requires-Python: >=3.9,<4.0
Classifier: Development Status :: 4 - Beta
Classifier: Intended Audience :: Developers
Classifier: License :: OSI Approved :: BSD License
Classifier: Operating System :: OS Independent
Classifier: Programming Language :: Python :: 3
Classifier: Programming Language :: Python :: 3.9
Classifier: Programming Language :: Python :: 3.10
Classifier: Programming Language :: Python :: 3.11
Classifier: Programming Language :: Python :: 3.12
Classifier: Programming Language :: Python :: 3 :: Only
Classifier: Programming Language :: Python :: 3.13
Classifier: Programming Language :: Python :: Implementation :: CPython
Classifier: Programming Language :: Python :: Implementation :: PyPy
Classifier: Typing :: Typed
Requires-Dist: more-itertools (>=4.0)
Requires-Dist: typing-extensions (>=4.4)
Project-URL: Bug Tracker, https://github.com/dargueta/binobj/issues
Project-URL: Documentation, https://dargueta.github.io/binobj
Project-URL: Homepage, https://dargueta.github.io/binobj
Project-URL: Repository, https://github.com/dargueta/binobj
